selenium2mysql/__init__.py
selenium2mysql/crawltools.py
selenium2mysql/info.py
selenium2mysql/json2mysql.py
selenium2mysql/loop.py
selenium2mysql/queue_manager.py
selenium2mysql/selenium_crawler.py
selenium2mysql/selenium_crawler_for_phantom.py
selenium2mysql-1.5.8.dist-info/LICENSE
selenium2mysql-1.5.8.dist-info/METADATA
selenium2mysql-1.5.8.dist-info/WHEEL
selenium2mysql-1.5.8.dist-info/top_level.txt
selenium2mysql-1.5.8.dist-info/RECORD
