Metadata-Version: 2.1
Name: selenium2mysql
Version: 1.5.8
Summary: scraper using selenium for general purposes
Home-page: https://github.com/hoosiki/selenium2mysql
Author: Junsang Park
Author-email: publichey@gmail.com
License: BSD
Download-URL: https://github.com/hoosiki/selenium2mysql/blob/master/dist/selenium2mysql-1.5.8.tar.gz
Platform: UNKNOWN
Requires-Dist: csv2sqllike
Requires-Dist: selenium
Requires-Dist: dict
Requires-Dist: validators
Requires-Dist: bs4
Requires-Dist: tqdm
